Workbook

Sheet Mode d'emploi
A1: Cahier de recette : EGUITRA Finance et AxisPro Suite
A2: Offre OTF-EGUITRA-2026-37 · E-VOLUTION XP
A4: Objet
A5: Vérifier avec les référents, sur l'environnement de recette, chaque attente de l'offre avant la mise en production.
A7: Où et avec quels comptes
A8: Environnement de recette (adresse remise par le prestataire), avec les comptes personnels de recette de chaque référent.
A9: Les données de recette sont une copie ou un extrait des données réelles : rien de ce qui est saisi en recette n'atteint la production.
A11: Comment remplir l'onglet Scénarios
A12: 1. Jouer le scénario tel qu'il est décrit, avec les données d'essai indiquées.
A13: 2. Noter le résultat obtenu, puis choisir le statut : OK, KO ou Réserve (écart mineur accepté).
A14: 3. Indiquer ses initiales et la date. En cas de KO, décrire l'écart dans le commentaire : le prestataire corrige, le scénario est rejoué.
A16: Décision de mise en production
... A18: Le procès-verbal de recette reprend la synthèse et la liste des réserves.

Sheet Scénarios
A1: N° | B1: Attente | C1: Profil | D1: Écran | E1: Scénario | F1: Données d'essai | G1: Résultat attendu | H1: Résultat obtenu | I1: Statut | J1: Testé par | K1: Date | L1: Commentaire
A2: R01 | B2: 1 | C2: Direction | D2: Finance > Tableau de bord | E2: Noter le CA du mois ; faire saisir et valider une facture de vente par la finance ; rouvrir le tableau de bord. | F2: Facture de 10 000 000 GNF HT | G2: Le CA du mois augmente de 10 000 000 GNF ; l'encours client augmente du montant TTC.
A3: R02 | B3: 1 | C3: Direction | D3: Finance > Rapport mensuel | E3: Choisir le mois écoulé, imprimer le rapport. | F3: — | G3: Rapport complet : indicateurs, résultat du mois et cumulé comparés à N-1, activités, flux, trésorerie, transport, alertes.
A4: R03 | B4: 2 | C4: Direction (compte ouvert aux deux sociétés) | D4: En-tête : sélecteur de société | E4: Passer d'EGUITRA GROUP SARLU à MB AxisPro, puis revenir. | F4: — | G4: L'écran se recharge ; seules les pièces de la société choisie apparaissent, jamais celles de l'autre.
A5: R04 | B5: 2 | C5: Direction | D5: Tableau de bord : « Groupe consolidé » | E5: Comparer les indicateurs en vue Société et en vue Groupe. | F5: — | G5: Le groupe réunit les deux sociétés ; chaque société garde ses propres montants.
A6: R05 | B6: 2 | C6: Administration | D6: Administration > Utilisateurs | E6: Créer un utilisateur ouvert aux deux sociétés et un autre ouvert au cabinet seulement ; se connecter avec chacun. | F6: Profil finance | G6: Le premier voit le sélecteur et les deux sociétés ; le second ne voit que MB AxisPro.
A7: R06 | B7: 2 | C7: Finance | D7: Activités et budget | E7: Afficher la marge par activité, chantier, ensemble routier et route. | F7: Données reprises | G7: Montants cohérents avec les écritures imputées.
A8: R07 | B8: 3 | C8: Finance | D8: Balance et états > Bilan | E8: Arrêté au dernier jour du mois écoulé. | F8: — | G8: Bilan équilibré (actif = passif) ; aucun compte « hors états ».
A9: R08 | B9: 3 | C9: Finance | D9: Balance et états > Compte de résultat | E9: Exercice en cours, comparaison à N-1. | F9: — | G9: Soldes intermédiaires (marge, valeur ajoutée, EBE, résultat) conformes à la balance.
A10: R09 | B10: 3 | C10: Finance | D10: Balance et états > Tableau des flux | E10: Exercice en cours. | F10: — | G10: Le tableau rejoint la trésorerie nette du bilan (écart nul).
A11: R10 | B11: 3 | C11: Finance et expert-comptable | D11: Balance et états > Balance | E11: Comparer la balance d'ouverture reprise à la balance de clôture de l'ancien système. | F11: Balance au 31/12/2025 | G11: Soldes identiques compte par compte, pour chaque société.
A12: R11 | B12: 3 | C12: Finance | D12: Reprise de l'exercice 2026 | E12: Contrôler les écritures et les rotations reprises. | F12: Classeur 2026 | G12: Balances mensuelles, nombre de rotations et chiffre d'affaires conformes au classeur.
A13: R12 | B13: 4 | C13: Exploitation | D13: Transport | E13: Valider puis facturer une rotation. | F13: — | G13: La facture porte l'activité transport, l'ensemble routier et la route ; la marge apparaît par ensemble et par route.
... A77: A11 | B77: AX | C77: Direction (société du groupe seule) | D77: AxisPro Suite | E77: Ouvrir AxisPro Suite avec un compte de direction ouvert à la seule société du groupe. | F77: — | G77: Aucun dossier, aucune pièce, revue ni grille du cabinet visible.

Sheet Synthèse
A1: Attente | B1: Libellé | C1: Scénarios | D1: OK | E1: Réserve | F1: KO | G1: Non joués
A2: 1 | B2: Visibilité temps réel : CA, résultat, trésorerie | C2: =COUNTIF('Scénarios'!$B$2:$B$77,"1") | D2: =COUNTIFS('Scénarios'!$B$2:$B$77,"1",'Scénarios'!$I$2:$I$77,"OK") | E2: =COUNTIFS('Scénarios'!$B$2:$B$77,"1",'Scénarios'!$I$2:$I$77,"Réserve") | F2: =COUNTIFS('Scénarios'!$B$2:$B$77,"1",'Scénarios'!$I$2:$I$77,"KO") | G2: =C2-D2-E2-F2
A3: 2 | B3: Vue consolidée, multi-sociétés, décomposable | C3: =COUNTIF('Scénarios'!$B$2:$B$77,"2") | D3: =COUNTIFS('Scénarios'!$B$2:$B$77,"2",'Scénarios'!$I$2:$I$77,"OK") | E3: =COUNTIFS('Scénarios'!$B$2:$B$77,"2",'Scénarios'!$I$2:$I$77,"Réserve") | F3: =COUNTIFS('Scénarios'!$B$2:$B$77,"2",'Scénarios'!$I$2:$I$77,"KO") | G3: =C3-D3-E3-F3
A4: 3 | B4: Comptabilité SYSCOHADA révisé | C4: =COUNTIF('Scénarios'!$B$2:$B$77,"3") | D4: =COUNTIFS('Scénarios'!$B$2:$B$77,"3",'Scénarios'!$I$2:$I$77,"OK") | E4: =COUNTIFS('Scénarios'!$B$2:$B$77,"3",'Scénarios'!$I$2:$I$77,"Réserve") | F4: =COUNTIFS('Scénarios'!$B$2:$B$77,"3",'Scénarios'!$I$2:$I$77,"KO") | G4: =C4-D4-E4-F4
A5: 4 | B5: Analytique par centre de coût, chantier, activité | C5: =COUNTIF('Scénarios'!$B$2:$B$77,"4") | D5: =COUNTIFS('Scénarios'!$B$2:$B$77,"4",'Scénarios'!$I$2:$I$77,"OK") | E5: =COUNTIFS('Scénarios'!$B$2:$B$77,"4",'Scénarios'!$I$2:$I$77,"Réserve") | F5: =COUNTIFS('Scénarios'!$B$2:$B$77,"4",'Scénarios'!$I$2:$I$77,"KO") | G5: =C5-D5-E5-F5
A6: 5 | B6: Trésorerie et rapprochement bancaire | C6: =COUNTIF('Scénarios'!$B$2:$B$77,"5") | D6: =COUNTIFS('Scénarios'!$B$2:$B$77,"5",'Scénarios'!$I$2:$I$77,"OK") | E6: =COUNTIFS('Scénarios'!$B$2:$B$77,"5",'Scénarios'!$I$2:$I$77,"Réserve") | F6: =COUNTIFS('Scénarios'!$B$2:$B$77,"5",'Scénarios'!$I$2:$I$77,"KO") | G6: =C6-D6-E6-F6
A7: 6 | B7: Immobilisations et amortissements | C7: =COUNTIF('Scénarios'!$B$2:$B$77,"6") | D7: =COUNTIFS('Scénarios'!$B$2:$B$77,"6",'Scénarios'!$I$2:$I$77,"OK") | E7: =COUNTIFS('Scénarios'!$B$2:$B$77,"6",'Scénarios'!$I$2:$I$77,"Réserve") | F7: =COUNTIFS('Scénarios'!$B$2:$B$77,"6",'Scénarios'!$I$2:$I$77,"KO") | G7: =C7-D7-E7-F7
A8: 7 | B8: Budget, écarts réalisé et prévisionnel | C8: =COUNTIF('Scénarios'!$B$2:$B$77,"7") | D8: =COUNTIFS('Scénarios'!$B$2:$B$77,"7",'Scénarios'!$I$2:$I$77,"OK") | E8: =COUNTIFS('Scénarios'!$B$2:$B$77,"7",'Scénarios'!$I$2:$I$77,"Réserve") | F8: =COUNTIFS('Scénarios'!$B$2:$B$77,"7",'Scénarios'!$I$2:$I$77,"KO") | G8: =C8-D8-E8-F8
A9: 8 | B9: Facturation clients et fournisseurs | C9: =COUNTIF('Scénarios'!$B$2:$B$77,"8") | D9: =COUNTIFS('Scénarios'!$B$2:$B$77,"8",'Scénarios'!$I$2:$I$77,"OK") | E9: =COUNTIFS('Scénarios'!$B$2:$B$77,"8",'Scénarios'!$I$2:$I$77,"Réserve") | F9: =COUNTIFS('Scénarios'!$B$2:$B$77,"8",'Scénarios'!$I$2:$I$77,"KO") | G9: =C9-D9-E9-F9
A10: 9 | B10: Fiscalité, TVA, déclarations | C10: =COUNTIF('Scénarios'!$B$2:$B$77,"9") | D10: =COUNTIFS('Scénarios'!$B$2:$B$77,"9",'Scénarios'!$I$2:$I$77,"OK") | E10: =COUNTIFS('Scénarios'!$B$2:$B$77,"9",'Scénarios'!$I$2:$I$77,"Réserve") | F10: =COUNTIFS('Scénarios'!$B$2:$B$77,"9",'Scénarios'!$I$2:$I$77,"KO") | G10: =C10-D10-E10-F10
A11: 10 | B11: Approbation des engagements et paiements | C11: =COUNTIF('Scénarios'!$B$2:$B$77,"10") | D11: =COUNTIFS('Scénarios'!$B$2:$B$77,"10",'Scénarios'!$I$2:$I$77,"OK") | E11: =COUNTIFS('Scénarios'!$B$2:$B$77,"10",'Scénarios'!$I$2:$I$77,"Réserve") | F11: =COUNTIFS('Scénarios'!$B$2:$B$77,"10",'Scénarios'!$I$2:$I$77,"KO") | G11: =C11-D11-E11-F11
A12: 11 | B12: Coûts et rentabilité transport | C12: =COUNTIF('Scénarios'!$B$2:$B$77,"11") | D12: =COUNTIFS('Scénarios'!$B$2:$B$77,"11",'Scénarios'!$I$2:$I$77,"OK") | E12: =COUNTIFS('Scénarios'!$B$2:$B$77,"11",'Scénarios'!$I$2:$I$77,"Réserve") | F12: =COUNTIFS('Scénarios'!$B$2:$B$77,"11",'Scénarios'!$I$2:$I$77,"KO") | G12: =C12-D12-E12-F12
A13: 12 | B13: Chantiers, avancement, retenues | C13: =COUNTIF('Scénarios'!$B$2:$B$77,"12") | D13: =COUNTIFS('Scénarios'!$B$2:$B$77,"12",'Scénarios'!$I$2:$I$77,"OK") | E13: =COUNTIFS('Scénarios'!$B$2:$B$77,"12",'Scénarios'!$I$2:$I$77,"Réserve") | F13: =COUNTIFS('Scénarios'!$B$2:$B$77,"12",'Scénarios'!$I$2:$I$77,"KO") | G13: =C13-D13-E13-F13
A14: 13 | B14: Gestion locative et patrimoine | C14: =COUNTIF('Scénarios'!$B$2:$B$77,"13") | D14: =COUNTIFS('Scénarios'!$B$2:$B$77,"13",'Scénarios'!$I$2:$I$77,"OK") | E14: =COUNTIFS('Scénarios'!$B$2:$B$77,"13",'Scénarios'!$I$2:$I$77,"Réserve") | F14: =COUNTIFS('Scénarios'!$B$2:$B$77,"13",'Scénarios'!$I$2:$I$77,"KO") | G14: =C14-D14-E14-F14
A15: 14 | B15: Traçabilité, piste d'audit | C15: =COUNTIF('Scénarios'!$B$2:$B$77,"14") | D15: =COUNTIFS('Scénarios'!$B$2:$B$77,"14",'Scénarios'!$I$2:$I$77,"OK") | E15: =COUNTIFS('Scénarios'!$B$2:$B$77,"14",'Scénarios'!$I$2:$I$77,"Réserve") | F15: =COUNTIFS('Scénarios'!$B$2:$B$77,"14",'Scénarios'!$I$2:$I$77,"KO") | G15: =C15-D15-E15-F15
A16: 15 | B16: Sécurité des accès par profil | C16: =COUNTIF('Scénarios'!$B$2:$B$77,"15") | D16: =COUNTIFS('Scénarios'!$B$2:$B$77,"15",'Scénarios'!$I$2:$I$77,"OK") | E16: =COUNTIFS('Scénarios'!$B$2:$B$77,"15",'Scénarios'!$I$2:$I$77,"Réserve") | F16: =COUNTIFS('Scénarios'!$B$2:$B$77,"15",'Scénarios'!$I$2:$I$77,"KO") | G16: =C16-D16-E16-F16
A17: 16 | B17: Disponibilité et sauvegardes | C17: =COUNTIF('Scénarios'!$B$2:$B$77,"16") | D17: =COUNTIFS('Scénarios'!$B$2:$B$77,"16",'Scénarios'!$I$2:$I$77,"OK") | E17: =COUNTIFS('Scénarios'!$B$2:$B$77,"16",'Scénarios'!$I$2:$I$77,"Réserve") | F17: =COUNTIFS('Scénarios'!$B$2:$B$77,"16",'Scénarios'!$I$2:$I$77,"KO") | G17: =C17-D17-E17-F17
A18: 17 | B18: Interface simple et formation | C18: =COUNTIF('Scénarios'!$B$2:$B$77,"17") | D18: =COUNTIFS('Scénarios'!$B$2:$B$77,"17",'Scénarios'!$I$2:$I$77,"OK") | E18: =COUNTIFS('Scénarios'!$B$2:$B$77,"17",'Scénarios'!$I$2:$I$77,"Réserve") | F18: =COUNTIFS('Scénarios'!$B$2:$B$77,"17",'Scénarios'!$I$2:$I$77,"KO") | G18: =C18-D18-E18-F18
A19: 18 | B19: Support et accompagnement | C19: =COUNTIF('Scénarios'!$B$2:$B$77,"18") | D19: =COUNTIFS('Scénarios'!$B$2:$B$77,"18",'Scénarios'!$I$2:$I$77,"OK") | E19: =COUNTIFS('Scénarios'!$B$2:$B$77,"18",'Scénarios'!$I$2:$I$77,"Réserve") | F19: =COUNTIFS('Scénarios'!$B$2:$B$77,"18",'Scénarios'!$I$2:$I$77,"KO") | G19: =C19-D19-E19-F19
A20: 19 | B20: Solution évolutive | C20: =COUNTIF('Scénarios'!$B$2:$B$77,"19") | D20: =COUNTIFS('Scénarios'!$B$2:$B$77,"19",'Scénarios'!$I$2:$I$77,"OK") | E20: =COUNTIFS('Scénarios'!$B$2:$B$77,"19",'Scénarios'!$I$2:$I$77,"Réserve") | F20: =COUNTIFS('Scénarios'!$B$2:$B$77,"19",'Scénarios'!$I$2:$I$77,"KO") | G20: =C20-D20-E20-F20
A21: AX | B21: AxisPro Suite et portail des porteurs | C21: =COUNTIF('Scénarios'!$B$2:$B$77,"AX") | D21: =COUNTIFS('Scénarios'!$B$2:$B$77,"AX",'Scénarios'!$I$2:$I$77,"OK") | E21: =COUNTIFS('Scénarios'!$B$2:$B$77,"AX",'Scénarios'!$I$2:$I$77,"Réserve") | F21: =COUNTIFS('Scénarios'!$B$2:$B$77,"AX",'Scénarios'!$I$2:$I$77,"KO") | G21: =C21-D21-E21-F21
B22: Total | C22: =SUM(C2:C21) | D22: =SUM(D2:D21) | E22: =SUM(E2:E21) | F22: =SUM(F2:F21) | G22: =SUM(G2:G21)
B24: Attente 20 (tarification claire) : vérifiée sur l'offre, sans scénario.
